README.rst
setup.py
gitvier/__init__.py
gitvier/cli.py
gitvier/commands.py
gitvier/common.py
gitvier/config.py
gitvier/exceptions.py
gitvier/logger.py
gitvier.egg-info/PKG-INFO
gitvier.egg-info/SOURCES.txt
gitvier.egg-info/dependency_links.txt
gitvier.egg-info/entry_points.txt
gitvier.egg-info/requires.txt
gitvier.egg-info/top_level.txt