Metadata-Version: 1.1
Name: gitvier
Version: 0.1.1
Summary: A component manager based where your components live in Git.
Home-page: https://github.com/MasterOdin/gitvier
Author: Matthew Peveler
Author-email: matt.peveler@gmail.com
License: MIT
Platform: UNKNOWN
Classifier: Development Status :: 2 - Pre-Alpha
Classifier: Environment :: Console
Classifier: Intended Audience :: Developers
Classifier: License :: OSI Approved :: MIT License
Classifier: Natural Language :: English
Classifier: Operating System :: OS Independent
Classifier: Programming Language :: Python
Classifier: Programming Language :: Python :: 3
Classifier: Topic :: Software Development
Classifier: Topic :: Software Development :: Build Tools
Classifier: Topic :: Software Development :: Version Control
Classifier: Topic :: System :: Software Distribution
